{
  "Author": "Abid",
  "For Update": "DM me on Telegram @MAbidOfficial",
  "last_update": "22-10-2025 : 01:28:37",
  "total_links": 1,
  "events": [
    {
      "title": "Perth Scorchers Women vs Sydney Sixers Women",
      "thumbnail": "https://static-files.cricket-australia.pulselive.com/series-web/60/3197.png",
      "status": "Live",
      "toss_result": "Perth Scorchers Women need 46 runs from 49 balls",
      "venue": "Cricket Central, Sydney Olympic Park",
      "match_link": "https://www.cricket.com.au/matches/CA:24357/perth-scorchers-women-sydney-sixers-women-t20-spring-challenge-2025-26",
      "m3u8_link": ""
    }
  ]
}